<?xml version="1.0" encoding="UTF-8" standalone="no"?><data>
    <user>
        <username>tung</username>
        <password>tung123</password>
    </user>
    <user>
        <username>tunglt</username>
        <password>tung123</password>
    </user>
    <user>
        <username>tung123</username>
        <password>tung123</password>
    </user>
    <user>
        <username>tungltt</username>
        <password>tung123</password>
    </user>
<user><username>a</username><password>123</password></user><user><username>truong</username><password>123123</password></user><user><username>b</username><password>123</password></user><user><username>truong123</username><password>123123</password></user><user><username>tri</username><password>123</password></user></data>